srad/__init__.py
srad/__main__.py
srad-0.1.1.dist-info/licenses/LICENSE
srad-0.1.1.dist-info/METADATA
srad-0.1.1.dist-info/WHEEL
srad-0.1.1.dist-info/top_level.txt
srad-0.1.1.dist-info/RECORD
