Metadata-Version: 2.4
Name: srad
Version: 0.1.1
Summary: Speckle Reducing Anisotropic Diffusion - Python implementation
Home-page: https://github.com/Keno-00/Speckle-Reducing-Anisotropic-Diffusion-SRAD
Author: Keno S. Jose
Author-email: 
Project-URL: Original MATLAB Implementation, https://github.com/Xingorno/Speckle-Reducing-Anisotropic-Diffusion-SRAD
Project-URL: Bug Tracker, https://github.com/Keno-00/Speckle-Reducing-Anisotropic-Diffusion-SRAD/issues
Keywords: srad speckle denoising anisotropic diffusion ultrasound image-processing
Classifier: Programming Language :: Python :: 3
Classifier: License :: OSI Approved :: MIT License
Classifier: Operating System :: OS Independent
Classifier: Topic :: Scientific/Engineering :: Image Processing
Classifier: Topic :: Scientific/Engineering :: Medical Science Apps.
Requires-Python: >=3.6
License-File: LICENSE
Requires-Dist: numpy
Requires-Dist: opencv-python
Dynamic: author
Dynamic: classifier
Dynamic: description
Dynamic: description-content-type
Dynamic: home-page
Dynamic: keywords
Dynamic: license-file
Dynamic: project-url
Dynamic: requires-dist
Dynamic: requires-python
Dynamic: summary
